{
  "fecha": "2025-11-13",
  "hora": "21:00",
  "cancha": "Por Confirmar",
  "metodo": "Posiciones Específicas (7 posiciones)",
  "rojo": [
    "Camilo",
    "Enrique",
    "Luis F",
    "Marco",
    "Carlos P",
    "Félix",
    "Vicente"
  ],
  "negro": [
    "Maxi Vargas",
    "Francisco H",
    "Pablo",
    "Ruben",
    "Juan R",
    "Iván",
    "Felipe"
  ],
  "promedio_rojo": 7.01,
  "promedio_negro": 7.01,
  "diferencia": 0.0,
  "rojo_posiciones": {
    "Camilo": "Arquero",
    "Marco": "Defensa",
    "Luis F": "Defensa",
    "Enrique": "Mediocampo",
    "Carlos P": "Mediocampo",
    "Vicente": "Mediocampo",
    "Félix": "Delantero"
  },
  "negro_posiciones": {
    "Maxi Vargas": "Arquero",
    "Pablo": "Defensa",
    "Ruben": "Defensa",
    "Felipe": "Mediocampo",
    "Juan R": "Mediocampo",
    "Iván": "Mediocampo",
    "Francisco H": "Delantero"
  },
  "equipos": {
    "rojo": [
      "Camilo",
      "Enrique",
      "Luis F",
      "Marco",
      "Carlos P",
      "Félix",
      "Vicente"
    ],
    "negro": [
      "Maxi Vargas",
      "Francisco H",
      "Pablo",
      "Ruben",
      "Juan R",
      "Iván",
      "Felipe"
    ]
  },
  "formaciones": {
    "rojo": "1-2-3-1",
    "negro": "1-2-3-1"
  },
  "puntajes": {
    "rojo": 49.1,
    "negro": 49.1,
    "diferencia": 0.0
  },
  "posiciones": {
    "rojo": [
      [
        "Camilo",
        "GK",
        7.5
      ],
      [
        "Marco",
        "LCB",
        7.0
      ],
      [
        "Luis F",
        "RCB",
        7.3
      ],
      [
        "Enrique",
        "LM",
        8.0
      ],
      [
        "Carlos P",
        "CM",
        6.5
      ],
      [
        "Vicente",
        "RM",
        8.0
      ],
      [
        "Félix",
        "CF",
        4.8
      ]
    ],
    "negro": [
      [
        "Maxi Vargas",
        "GK",
        7.2
      ],
      [
        "Pablo",
        "LCB",
        7.5
      ],
      [
        "Ruben",
        "RCB",
        6.6
      ],
      [
        "Felipe",
        "LM",
        7.5
      ],
      [
        "Juan R",
        "CM",
        5.8
      ],
      [
        "Iván",
        "RM",
        6.3
      ],
      [
        "Francisco H",
        "CF",
        8.2
      ]
    ]
  }
}